GC_SFTP_DBPOSTGRES/__init__.py
GC_SFTP_DBPOSTGRES/carga_datos_efficient.py
GC_SFTP_DBPOSTGRES/config.py
GC_SFTP_DBPOSTGRES/logging_config.py
GC_SFTP_DBPOSTGRES/logging_utils.py
GC_SFTP_DBPOSTGRES/s3_uploader.py
GC_SFTP_DBPOSTGRES-0.9.10.dist-info/METADATA
GC_SFTP_DBPOSTGRES-0.9.10.dist-info/WHEEL
GC_SFTP_DBPOSTGRES-0.9.10.dist-info/top_level.txt
GC_SFTP_DBPOSTGRES-0.9.10.dist-info/RECORD
