Metadata-Version: 2.1
Name: GC_SFTP_DBPOSTGRES
Version: 0.9.10
Summary: Paquete para optimizar la carga y transferencia de datos a PostgreSQL y S3
Home-page: https://github.com/tu_usuario/GC_SFTP_DBPOSTGRES
Author: Giancarlos Cardenas
Author-email: gcardenas@bim.pe
Requires-Dist: boto3
Requires-Dist: psycopg2-binary
Requires-Dist: pandas
Requires-Dist: configparser
